{"pageProps":{"__CLIENT_CACHE_PROP":"{\"cache\":{\"generalSettings\":{\"__typename\":\"GeneralSettings\",\"title\":\"Apria\",\"description\":\"\"},\"posts_f30bc_f5980\":{\"__typename\":\"RootQueryToPostConnection\",\"nodes\":[{\"__typename\":\"Post\",\"id\":\"cG9zdDo2MDkz\",\"slug\":\"interview-with-jack-bardwell\",\"featuredImage\":{\"__typename\":\"NodeWithFeaturedImageToMediaItemConnectionEdge\",\"node\":{\"__typename\":\"MediaItem\",\"id\":\"cG9zdDo2MzM2\",\"mediaItemUrl\":\"https://apriatst.artez.nl/wp-content/uploads/2023/03/mushroom_radio_grad_show-1024x683-1.jpg\"}},\"title_b28e9_bf21a\":\"Interview with Jack Bardwell\"},{\"__typename\":\"Post\",\"id\":\"cG9zdDo2MDQ0\",\"slug\":\"interview-met-willem-van-weelden\",\"featuredImage\":null,\"title_b28e9_bf21a\":\"Interview met Willem van Weelden\"},{\"__typename\":\"Post\",\"id\":\"cG9zdDo2MDYy\",\"slug\":\"teaching-art-episode-3\",\"featuredImage\":null,\"title_b28e9_bf21a\":\"Teaching Art Episode 3\"},{\"__typename\":\"Post\",\"id\":\"cG9zdDo2MDcz\",\"slug\":\"teaching-art-episode-2\",\"featuredImage\":null,\"title_b28e9_bf21a\":\"Teaching Art Episode 2\"},{\"__typename\":\"Post\",\"id\":\"cG9zdDo2MDA1\",\"slug\":\"interview-met-sophie-krier\",\"featuredImage\":{\"__typename\":\"NodeWithFeaturedImageToMediaItemConnectionEdge\",\"node\":{\"__typename\":\"MediaItem\",\"id\":\"cG9zdDo2MzM4\",\"mediaItemUrl\":\"https://apriatst.artez.nl/wp-content/uploads/2023/02/2021_ISOTP-HNI-Berlijn-photoErikWong-1024x768-1.jpeg\"}},\"title_b28e9_bf21a\":\"Interview met Sophie Krier\"},{\"__typename\":\"Post\",\"id\":\"cG9zdDo1OTc2\",\"slug\":\"interview-met-pascal-van-gielen\",\"featuredImage\":null,\"title_b28e9_bf21a\":\"Interview met Pascal Gielen\"},{\"__typename\":\"Post\",\"id\":\"cG9zdDo1OTk1\",\"slug\":\"whispers-from-the-past\",\"featuredImage\":null,\"title_b28e9_bf21a\":\"Whispers from the Past\"},{\"__typename\":\"Post\",\"id\":\"cG9zdDo1OTM3\",\"slug\":\"doing-things-with-stories-2\",\"featuredImage\":null,\"title_b28e9_bf21a\":\"Doing Things with Stories: Introduction\"},{\"__typename\":\"Post\",\"id\":\"cG9zdDo1ODUw\",\"slug\":\"doing-things-with-stories\",\"featuredImage\":null,\"title_b28e9_bf21a\":\"Doing Things with Stories: Editorial\"},{\"__typename\":\"Post\",\"id\":\"cG9zdDo1ODc2\",\"slug\":\"the-genesis\",\"featuredImage\":null,\"title_b28e9_bf21a\":\"The Genesis\"},{\"__typename\":\"Post\",\"id\":\"cG9zdDo1ODI4\",\"slug\":\"the-other-side-of-the-river\",\"featuredImage\":{\"__typename\":\"NodeWithFeaturedImageToMediaItemConnectionEdge\",\"node\":{\"__typename\":\"MediaItem\",\"id\":\"cG9zdDo2MzQw\",\"mediaItemUrl\":\"https://apriatst.artez.nl/wp-content/uploads/2023/02/INTRODUCTION-768x1024-1.jpg\"}},\"title_b28e9_bf21a\":\"THE OTHER SIDE OF THE RIVER\"},{\"__typename\":\"Post\",\"id\":\"cG9zdDo1ODQ0\",\"slug\":\"shadow-reverie\",\"featuredImage\":null,\"title_b28e9_bf21a\":\"Shadow Reverie\"},{\"__typename\":\"Post\",\"id\":\"cG9zdDo1ODg2\",\"slug\":\"taking-charge-of-their-own-narratives\",\"featuredImage\":null,\"title_b28e9_bf21a\":\"Taking Charge of Their Own Narratives\"},{\"__typename\":\"Post\",\"id\":\"cG9zdDo1ODM4\",\"slug\":\"gauteng-maboneng-jozi-my-home\",\"featuredImage\":null,\"title_b28e9_bf21a\":\"Gauteng Maboneng, Jozi, my home\"},{\"__typename\":\"Post\",\"id\":\"cG9zdDo1OTQz\",\"slug\":\"teaching-art\",\"featuredImage\":null,\"title_b28e9_bf21a\":\"Teaching Art Episode 1\"},{\"__typename\":\"Post\",\"id\":\"cG9zdDo1ODcz\",\"slug\":\"the-missing-diary-of-the-portrait-of-lisa-and-ella\",\"featuredImage\":null,\"title_b28e9_bf21a\":\"THE MISSING DIARY OF THE PORTRAIT OF LISA AND ELLA\"},{\"__typename\":\"Post\",\"id\":\"cG9zdDo1ODY0\",\"slug\":\"imagining-a-ministry-for-the-future\",\"featuredImage\":null,\"title_b28e9_bf21a\":\"Imagining a Ministry for the Future\"},{\"__typename\":\"Post\",\"id\":\"cG9zdDo1ODk4\",\"slug\":\"narrative-change-practice-story\",\"featuredImage\":null,\"title_b28e9_bf21a\":\"Narrative Change Practice Story\"},{\"__typename\":\"Post\",\"id\":\"cG9zdDo1ODgw\",\"slug\":\"the-mask-that-saved-my-career\",\"featuredImage\":null,\"title_b28e9_bf21a\":\"The Mask that Saved my Career\"},{\"__typename\":\"Post\",\"id\":\"cG9zdDo1ODIw\",\"slug\":\"carriers-of-dil\",\"featuredImage\":{\"__typename\":\"NodeWithFeaturedImageToMediaItemConnectionEdge\",\"node\":{\"__typename\":\"MediaItem\",\"id\":\"cG9zdDo2MzQy\",\"mediaItemUrl\":\"https://apriatst.artez.nl/wp-content/uploads/2023/02/one.png\"}},\"title_b28e9_bf21a\":\"Carriers of Dil\"},{\"__typename\":\"Post\",\"id\":\"cG9zdDo1ODQx\",\"slug\":\"the-blind-oracle\",\"featuredImage\":null,\"title_b28e9_bf21a\":\"The Blind Oracle\"}]}},\"selections\":[[[\"{\\\"after\\\":\\\"String\\\",\\\"before\\\":\\\"String\\\",\\\"first\\\":\\\"Int\\\",\\\"last\\\":\\\"Int\\\",\\\"where\\\":\\\"RootQueryToPostConnectionWhereArgs\\\"}\",\"f30bc\"],[\"{\\\"first\\\":21}\",\"f5980\"],[\"{\\\"after\\\":\\\"String\\\",\\\"before\\\":\\\"String\\\",\\\"first\\\":\\\"Int\\\",\\\"last\\\":\\\"Int\\\",\\\"where\\\":\\\"RootQueryToMenuItemConnectionWhereArgs\\\"}\",\"8d665\"],[\"{\\\"where\\\":{\\\"location\\\":\\\"PRIMARY\\\"}}\",\"12a43\"],[\"{\\\"format\\\":\\\"PostObjectFieldFormatEnum\\\"}\",\"b28e9\"],[\"{}\",\"bf21a\"]],\"v1\"]}","__AUTH_CLIENT_CACHE_PROP":"{}"},"__N_SSG":true}